[
    {
        "name": "Tennis Club de Saint Mandrier",
        "lat": 43.07776,
        "lng": 5.92895,
        "types": [
            "establishment"
        ]
    },
    {
        "name": "Tennis club Roy d'Espagne",
        "lat": 43.237347,
        "lng": 5.390217,
        "types": [
            "establishment"
        ]
    },
    {
        "name": "Tennis Loisirs Toursainte",
        "lat": 43.348585,
        "lng": 5.392024,
        "types": [
            "establishment"
        ]
    },
    {
        "name": "Tennis Club Pradetan",
        "lat": 43.105228,
        "lng": 6.014671,
        "types": [
            "store",
            "establishment"
        ]
    },
    {
        "name": "Tennis Club de Marseille",
        "lat": 43.267813,
        "lng": 5.380566,
        "types": [
            "establishment"
        ]
    },
    {
        "name": "Tennis Club CSMT La Coudouli\u00e8re",
        "lat": 43.10111,
        "lng": 5.823234,
        "types": [
            "establishment"
        ]
    },
    {
        "name": "Tennis Club Montval",
        "lat": 43.251949,
        "lng": 5.411344,
        "types": [
            "establishment"
        ]
    },
    {
        "name": "Tennis Park de Marseille",
        "lat": 43.301908,
        "lng": 5.492786,
        "types": [
            "establishment"
        ]
    },
    {
        "name": "Tennis Club St Cyrien",
        "lat": 43.18467,
        "lng": 5.682845,
        "types": [
            "establishment"
        ]
    },
    {
        "name": "Office Municipal de Tennis Club de G\u00e9menos",
        "lat": 43.287982,
        "lng": 5.617389,
        "types": [
            "bar",
            "school",
            "establishment"
        ]
    },
    {
        "name": "Tennis",
        "lat": 43.48903,
        "lng": 5.37827,
        "types": [
            "establishment"
        ]
    },
    {
        "name": "Tennis Club du Parc",
        "lat": 43.094123,
        "lng": 6.080211,
        "types": [
            "school",
            "establishment"
        ]
    },
    {
        "name": "TCA",
        "lat": 43.309222,
        "lng": 5.592629,
        "types": [
            "school",
            "establishment"
        ]
    },
    {
        "name": "Tennis Club Barban",
        "lat": 43.094808,
        "lng": 5.856782,
        "types": [
            "establishment"
        ]
    },
    {
        "name": "Tennis Club du Rosaire",
        "lat": 43.118166,
        "lng": 5.78922,
        "types": [
            "establishment"
        ]
    },
    {
        "name": "Tennis Club du Littoral",
        "lat": 43.114376,
        "lng": 5.941694,
        "types": [
            "establishment"
        ]
    },
    {
        "name": "Atelier du Tennis",
        "lat": 43.109999,
        "lng": 5.939369,
        "types": [
            "store",
            "establishment"
        ]
    },
    {
        "name": "Tennis du Val de l'Arc",
        "lat": 43.509957,
        "lng": 5.466253,
        "types": [
            "establishment"
        ]
    },
    {
        "name": "Tennis Club la Rouvi\u00e8re",
        "lat": 43.253857,
        "lng": 5.421426,
        "types": [
            "establishment"
        ]
    },
    {
        "name": "Tennis Club Gard\u00e9en",
        "lat": 43.132802,
        "lng": 6.024638,
        "types": [
            "establishment"
        ]
    },
    {
        "name": "Tennis Club Bocage",
        "lat": 43.339696,
        "lng": 5.4584,
        "types": [
            "establishment"
        ]
    },
    {
        "name": "Tennis Club Phoc\u00e9en",
        "lat": 43.238197,
        "lng": 5.430426,
        "types": [
            "establishment"
        ]
    },
    {
        "name": "William Tennis Club",
        "lat": 43.27244,
        "lng": 5.382557,
        "types": [
            "bar",
            "restaurant",
            "food",
            "establishment"
        ]
    },
    {
        "name": "ASPTT Hy\u00e8res Tennis",
        "lat": 43.108687,
        "lng": 6.178753,
        "types": [
            "establishment"
        ]
    },
    {
        "name": "Cercle Sportif Marseille Tennis",
        "lat": 43.266054,
        "lng": 5.390322,
        "types": [
            "establishment"
        ]
    },
    {
        "name": "Tennis Jean Becker",
        "lat": 43.274855,
        "lng": 5.394826,
        "types": [
            "establishment"
        ]
    },
    {
        "name": "Allaudien Tennis Club",
        "lat": 43.343217,
        "lng": 5.47863,
        "types": [
            "establishment"
        ]
    },
    {
        "name": "Tennis Club La Rose",
        "lat": 43.327368,
        "lng": 5.422228,
        "types": [
            "establishment"
        ]
    },
    {
        "name": "Tennis Club Municipal",
        "lat": 43.37586,
        "lng": 5.77895,
        "types": [
            "establishment"
        ]
    },
    {
        "name": "Tennis-Club de Ch\u00e2teau Gombert",
        "lat": 43.344086,
        "lng": 5.430535,
        "types": [
            "school",
            "establishment"
        ]
    },
    {
        "name": "Tennis Club la Val\u00e9riane - Sanary sur Mer",
        "lat": 43.126836,
        "lng": 5.797431,
        "types": [
            "establishment"
        ]
    },
    {
        "name": "Univers du Tennis",
        "lat": 43.154795,
        "lng": 6.045928,
        "types": [
            "store",
            "establishment"
        ]
    },
    {
        "name": "Tennis Club Hyerois",
        "lat": 43.110772,
        "lng": 6.137294,
        "types": [
            "establishment"
        ]
    },
    {
        "name": "Tennis Club Fuveau",
        "lat": 43.452265,
        "lng": 5.553235,
        "types": [
            "establishment"
        ]
    },
    {
        "name": "Tennis Club de Peynier",
        "lat": 43.44661,
        "lng": 5.633111,
        "types": [
            "establishment"
        ]
    },
    {
        "name": "Handi Tennis de Table Hy\u00e9rois",
        "lat": 43.114345,
        "lng": 6.14476,
        "types": [
            "establishment"
        ]
    },
    {
        "name": "Tennis Club N\u00e9grelien",
        "lat": 43.487921,
        "lng": 5.592495,
        "types": [
            "establishment"
        ]
    },
    {
        "name": "Tennis Sporting Club de Cassis",
        "lat": 43.229091,
        "lng": 5.534623,
        "types": [
            "establishment"
        ]
    },
    {
        "name": "Tennis club de la seyne sur mer",
        "lat": 43.0948,
        "lng": 5.856818,
        "types": [
            "establishment"
        ]
    },
    {
        "name": "Tennis Club de Vitrolles",
        "lat": 43.430118,
        "lng": 5.27824,
        "types": [
            "establishment"
        ]
    },
    {
        "name": "Tennis Club Pierrefeucain",
        "lat": 43.222639,
        "lng": 6.146464,
        "types": [
            "establishment"
        ]
    },
    {
        "name": "Tennis Club Municipal Six Four",
        "lat": 43.108891,
        "lng": 5.819578,
        "types": [
            "establishment"
        ]
    },
    {
        "name": "Tennis Club Gardannais",
        "lat": 43.46304,
        "lng": 5.480634,
        "types": [
            "establishment"
        ]
    },
    {
        "name": "Tennis Club Lorguais",
        "lat": 43.494617,
        "lng": 6.367553,
        "types": [
            "establishment"
        ]
    },
    {
        "name": "AS Tennis Ceyreste",
        "lat": 43.222536,
        "lng": 5.630217,
        "types": [
            "establishment"
        ]
    },
    {
        "name": "SMUC Tennis",
        "lat": 43.258949,
        "lng": 5.385332,
        "types": [
            "establishment"
        ]
    },
    {
        "name": "Ligue Provence Tennis",
        "lat": 43.569486,
        "lng": 5.418344,
        "types": [
            "establishment"
        ]
    },
    {
        "name": "Tennis Club de Bandol",
        "lat": 43.135385,
        "lng": 5.739724,
        "types": [
            "establishment"
        ]
    },
    {
        "name": "Tennis Club Saint Charles",
        "lat": 43.115196,
        "lng": 6.012459,
        "types": [
            "establishment"
        ]
    },
    {
        "name": "Animasport",
        "lat": 43.348385,
        "lng": 5.397886,
        "types": [
            "establishment"
        ]
    },
    {
        "name": "Association Tennis Club Gignac",
        "lat": 43.393345,
        "lng": 5.239183,
        "types": [
            "establishment"
        ]
    },
    {
        "name": "TENNIS DE TABLE LUCOIS",
        "lat": 43.390165,
        "lng": 6.320486,
        "types": [
            "establishment"
        ]
    },
    {
        "name": "Tennis Sporting Club de Cassis S.C.C.",
        "lat": 43.21784,
        "lng": 5.52899,
        "types": [
            "real_estate_agency",
            "establishment"
        ]
    },
    {
        "name": "Tennis Club Du Val D Issole",
        "lat": 43.339731,
        "lng": 5.990581,
        "types": [
            "establishment"
        ]
    },
    {
        "name": "Tennis Club De Forcalqueiret",
        "lat": 43.334145,
        "lng": 6.08238,
        "types": [
            "establishment"
        ]
    },
    {
        "name": "Mairie - tennis municipal ollioulais",
        "lat": 43.123402,
        "lng": 5.830376,
        "types": [
            "establishment"
        ]
    },
    {
        "name": "Tennis Club Cr\u00e9dit Agr",
        "lat": 43.08384,
        "lng": 5.837483,
        "types": [
            "establishment"
        ]
    },
    {
        "name": "Tennis Club Queirel",
        "lat": 43.280395,
        "lng": 5.43523,
        "types": [
            "establishment"
        ]
    },
    {
        "name": "La Ciotat Tennis Club",
        "lat": 43.196425,
        "lng": 5.63218,
        "types": [
            "bar",
            "establishment"
        ]
    },
    {
        "name": "Tennis Club Cuersois",
        "lat": 43.23602,
        "lng": 6.0759,
        "types": [
            "establishment"
        ]
    }
]